Workbook

Sheet Providers
A1: ProviderId | B1: Model (env default) | C1: Input $/Mtok | D1: Output $/Mtok | E1: Source / verify URL
A2: anthropic | B2: claude-haiku-4-5-20251001 | C2: 1 | D2: 5 | E2: https://www.anthropic.com/pricing — Haiku 4.5 (Oct 2025)
A3: anthropic-sonnet | B3: claude-sonnet-4-6 (fallback for deep ops) | C3: 3 | D3: 15 | E3: https://www.anthropic.com/pricing — Sonnet 4.6
A4: openai | B4: gpt-4o-mini | C4: 0.15 | D4: 0.6 | E4: https://openai.com/api/pricing — gpt-4o-mini
A5: gemini | B5: gemini-2.5-flash | C5: 0.3 | D5: 2.5 | E5: https://ai.google.dev/pricing — 2.5 Flash (NOT 1.5; margin_scenarios.py uses STALE 1.5 price)
A6: gemini-15 | B6: gemini-1.5-flash (legacy; retired in registry) | C6: 0.075 | D6: 0.3 | E6: https://ai.google.dev/pricing — 1.5 Flash

Sheet Ops
A1: Op | B1: Credits/call | C1: Input tokens | D1: Output tokens | E1: Current-policy primary | F1: Notes
A2: chat_turn | B2: 1 | C2: 1500 | D2: 400 | E2: openai | F2: ROUTING_POLICY.chat = [openai,anthropic,gemini]
A3: summarize | B3: 3 | C3: 8000 | D3: 600 | E3: anthropic | F3: ROUTING_POLICY.summarize = [anthropic,openai,gemini]
A4: translate | B4: 5 | C4: 3000 | D4: 3200 | E4: gemini | F4: ROUTING_POLICY.translate = [gemini,anthropic,openai]
A5: ocr | B5: 2 | C5: 500 | D5: 800 | E5: gemini | F5: ROUTING_POLICY.ocr = [gemini,anthropic] (pdfInput cap)
A6: compare | B6: 15 | C6: 15000 | D6: 2000 | E6: anthropic | F6: ROUTING_POLICY.compare = [anthropic,openai,gemini]
A7: rewrite | B7: 3 | C7: 4000 | D7: 4200 | E7: anthropic | F7: per AI_OPERATION_COSTS; routed as generate-class
A8: table | B8: 3 | C8: 6000 | D8: 1500 | E8: anthropic | F8: per AI_OPERATION_COSTS
A9: redact | B9: 5 | C9: 5000 | D9: 1000 | E9: anthropic | F9: per AI_OPERATION_COSTS
A10: generate | B10: 20 | C10: 2000 | D10: 8000 | E10: anthropic | F10: ROUTING_POLICY.generate = [anthropic,openai,gemini]
A11: sign | B11: 10 | C11: 1000 | D11: 1500 | E11: anthropic | F11: ROUTING_POLICY.sign = [anthropic,openai,gemini]

Sheet Cost Matrix
A1: Op | B1: Credits | C1: In tok | D1: Out tok | E1: Anthropic Haiku $/call | F1: OpenAI 4o-mini $/call | G1: Gemini 2.5 Flash $/call | H1: Cheapest $/call | I1: Current-policy $/call | J1: $ savings/call if re-routed
A2: =Ops!A2 -> chat_turn | B2: =Ops!B2 -> 1 | C2: =Ops!C2 -> 1500 | D2: =Ops!D2 -> 400 | E2: =(C2*Providers!$C$2+D2*Providers!$D$2)/1000000 -> 0.0035 | F2: =(C2*Providers!$C$4+D2*Providers!$D$4)/1000000 -> 0.000465 | G2: =(C2*Providers!$C$5+D2*Providers!$D$5)/1000000 -> 0.00145 | H2: =MIN(E2:G2) -> 0.000465 | I2: =IF(Ops!E2="anthropic",E2,IF(Ops!E2="openai",F2,G2)) -> 0.000465 | J2: =I2-H2 -> 0
A3: =Ops!A3 -> summarize | B3: =Ops!B3 -> 3 | C3: =Ops!C3 -> 8000 | D3: =Ops!D3 -> 600 | E3: =(C3*Providers!$C$2+D3*Providers!$D$2)/1000000 -> 0.011 | F3: =(C3*Providers!$C$4+D3*Providers!$D$4)/1000000 -> 0.00156 | G3: =(C3*Providers!$C$5+D3*Providers!$D$5)/1000000 -> 0.0039 | H3: =MIN(E3:G3) -> 0.00156 | I3: =IF(Ops!E3="anthropic",E3,IF(Ops!E3="openai",F3,G3)) -> 0.011 | J3: =I3-H3 -> 0.00944
A4: =Ops!A4 -> translate | B4: =Ops!B4 -> 5 | C4: =Ops!C4 -> 3000 | D4: =Ops!D4 -> 3200 | E4: =(C4*Providers!$C$2+D4*Providers!$D$2)/1000000 -> 0.019 | F4: =(C4*Providers!$C$4+D4*Providers!$D$4)/1000000 -> 0.00237 | G4: =(C4*Providers!$C$5+D4*Providers!$D$5)/1000000 -> 0.0089 | H4: =MIN(E4:G4) -> 0.00237 | I4: =IF(Ops!E4="anthropic",E4,IF(Ops!E4="openai",F4,G4)) -> 0.0089 | J4: =I4-H4 -> 0.00653
A5: =Ops!A5 -> ocr | B5: =Ops!B5 -> 2 | C5: =Ops!C5 -> 500 | D5: =Ops!D5 -> 800 | E5: =(C5*Providers!$C$2+D5*Providers!$D$2)/1000000 -> 0.0045 | F5: =(C5*Providers!$C$4+D5*Providers!$D$4)/1000000 -> 0.000555 | G5: =(C5*Providers!$C$5+D5*Providers!$D$5)/1000000 -> 0.00215 | H5: =MIN(E5:G5) -> 0.000555 | I5: =IF(Ops!E5="anthropic",E5,IF(Ops!E5="openai",F5,G5)) -> 0.00215 | J5: =I5-H5 -> 0.001595
A6: =Ops!A6 -> compare | B6: =Ops!B6 -> 15 | C6: =Ops!C6 -> 15000 | D6: =Ops!D6 -> 2000 | E6: =(C6*Providers!$C$2+D6*Providers!$D$2)/1000000 -> 0.025 | F6: =(C6*Providers!$C$4+D6*Providers!$D$4)/1000000 -> 0.00345 | G6: =(C6*Providers!$C$5+D6*Providers!$D$5)/1000000 -> 0.0095 | H6: =MIN(E6:G6) -> 0.00345 | I6: =IF(Ops!E6="anthropic",E6,IF(Ops!E6="openai",F6,G6)) -> 0.025 | J6: =I6-H6 -> 0.02155
A7: =Ops!A7 -> rewrite | B7: =Ops!B7 -> 3 | C7: =Ops!C7 -> 4000 | D7: =Ops!D7 -> 4200 | E7: =(C7*Providers!$C$2+D7*Providers!$D$2)/1000000 -> 0.025 | F7: =(C7*Providers!$C$4+D7*Providers!$D$4)/1000000 -> 0.00312 | G7: =(C7*Providers!$C$5+D7*Providers!$D$5)/1000000 -> 0.0117 | H7: =MIN(E7:G7) -> 0.00312 | I7: =IF(Ops!E7="anthropic",E7,IF(Ops!E7="openai",F7,G7)) -> 0.025 | J7: =I7-H7 -> 0.02188
A8: =Ops!A8 -> table | B8: =Ops!B8 -> 3 | C8: =Ops!C8 -> 6000 | D8: =Ops!D8 -> 1500 | E8: =(C8*Providers!$C$2+D8*Providers!$D$2)/1000000 -> 0.0135 | F8: =(C8*Providers!$C$4+D8*Providers!$D$4)/1000000 -> 0.0018 | G8: =(C8*Providers!$C$5+D8*Providers!$D$5)/1000000 -> 0.00555 | H8: =MIN(E8:G8) -> 0.0018 | I8: =IF(Ops!E8="anthropic",E8,IF(Ops!E8="openai",F8,G8)) -> 0.0135 | J8: =I8-H8 -> 0.0117
A9: =Ops!A9 -> redact | B9: =Ops!B9 -> 5 | C9: =Ops!C9 -> 5000 | D9: =Ops!D9 -> 1000 | E9: =(C9*Providers!$C$2+D9*Providers!$D$2)/1000000 -> 0.01 | F9: =(C9*Providers!$C$4+D9*Providers!$D$4)/1000000 -> 0.00135 | G9: =(C9*Providers!$C$5+D9*Providers!$D$5)/1000000 -> 0.004 | H9: =MIN(E9:G9) -> 0.00135 | I9: =IF(Ops!E9="anthropic",E9,IF(Ops!E9="openai",F9,G9)) -> 0.01 | J9: =I9-H9 -> 0.00865
A10: =Ops!A10 -> generate | B10: =Ops!B10 -> 20 | C10: =Ops!C10 -> 2000 | D10: =Ops!D10 -> 8000 | E10: =(C10*Providers!$C$2+D10*Providers!$D$2)/1000000 -> 0.042 | F10: =(C10*Providers!$C$4+D10*Providers!$D$4)/1000000 -> 0.0051 | G10: =(C10*Providers!$C$5+D10*Providers!$D$5)/1000000 -> 0.0206 | H10: =MIN(E10:G10) -> 0.0051 | I10: =IF(Ops!E10="anthropic",E10,IF(Ops!E10="openai",F10,G10)) -> 0.042 | J10: =I10-H10 -> 0.0369
A11: =Ops!A11 -> sign | B11: =Ops!B11 -> 10 | C11: =Ops!C11 -> 1000 | D11: =Ops!D11 -> 1500 | E11: =(C11*Providers!$C$2+D11*Providers!$D$2)/1000000 -> 0.0085 | F11: =(C11*Providers!$C$4+D11*Providers!$D$4)/1000000 -> 0.00105 | G11: =(C11*Providers!$C$5+D11*Providers!$D$5)/1000000 -> 0.00405 | H11: =MIN(E11:G11) -> 0.00105 | I11: =IF(Ops!E11="anthropic",E11,IF(Ops!E11="openai",F11,G11)) -> 0.0085 | J11: =I11-H11 -> 0.00745
A12: TOTAL (single-call basket) | E12: =SUM(E2:E11) -> 0.162 | F12: =SUM(F2:F11) -> 0.02082 | G12: =SUM(G2:G11) -> 0.0718 | H12: =SUM(H2:H11) -> 0.02082 | I12: =SUM(I2:I11) -> 0.146515 | J12: =SUM(J2:J11) -> 0.125695

Sheet Routing vs Best
A1: Op | B1: Current primary | C1: Cheapest provider | D1: Match? | E1: Current $/call | F1: Cheapest $/call | G1: Savings $/call | H1: Savings / 1k calls
A2: =Ops!A2 -> chat_turn | B2: =Ops!E2 -> openai | C2: =INDEX({"anthropic","openai","gemini"},MATCH(MIN('Cost Matrix'!E2:G2),'Cost Matrix'!E2:G2,0)) -> openai | D2: =IF(B2=C2,"✓","→ re-route") -> ✓ | E2: ='Cost Matrix'!I2 -> 0.000465 | F2: ='Cost Matrix'!H2 -> 0.000465 | G2: =E2-F2 -> 0 | H2: =G2*1000 -> 0
A3: =Ops!A3 -> summarize | B3: =Ops!E3 -> anthropic | C3: =INDEX({"anthropic","openai","gemini"},MATCH(MIN('Cost Matrix'!E3:G3),'Cost Matrix'!E3:G3,0)) -> openai | D3: =IF(B3=C3,"✓","→ re-route") -> → re-route | E3: ='Cost Matrix'!I3 -> 0.011 | F3: ='Cost Matrix'!H3 -> 0.00156 | G3: =E3-F3 -> 0.00944 | H3: =G3*1000 -> 9.44
A4: =Ops!A4 -> translate | B4: =Ops!E4 -> gemini | C4: =INDEX({"anthropic","openai","gemini"},MATCH(MIN('Cost Matrix'!E4:G4),'Cost Matrix'!E4:G4,0)) -> openai | D4: =IF(B4=C4,"✓","→ re-route") -> → re-route | E4: ='Cost Matrix'!I4 -> 0.0089 | F4: ='Cost Matrix'!H4 -> 0.00237 | G4: =E4-F4 -> 0.00653 | H4: =G4*1000 -> 6.53
A5: =Ops!A5 -> ocr | B5: =Ops!E5 -> gemini | C5: =INDEX({"anthropic","openai","gemini"},MATCH(MIN('Cost Matrix'!E5:G5),'Cost Matrix'!E5:G5,0)) -> openai | D5: =IF(B5=C5,"✓","→ re-route") -> → re-route | E5: ='Cost Matrix'!I5 -> 0.00215 | F5: ='Cost Matrix'!H5 -> 0.000555 | G5: =E5-F5 -> 0.001595 | H5: =G5*1000 -> 1.595
A6: =Ops!A6 -> compare | B6: =Ops!E6 -> anthropic | C6: =INDEX({"anthropic","openai","gemini"},MATCH(MIN('Cost Matrix'!E6:G6),'Cost Matrix'!E6:G6,0)) -> openai | D6: =IF(B6=C6,"✓","→ re-route") -> → re-route | E6: ='Cost Matrix'!I6 -> 0.025 | F6: ='Cost Matrix'!H6 -> 0.00345 | G6: =E6-F6 -> 0.02155 | H6: =G6*1000 -> 21.55
A7: =Ops!A7 -> rewrite | B7: =Ops!E7 -> anthropic | C7: =INDEX({"anthropic","openai","gemini"},MATCH(MIN('Cost Matrix'!E7:G7),'Cost Matrix'!E7:G7,0)) -> openai | D7: =IF(B7=C7,"✓","→ re-route") -> → re-route | E7: ='Cost Matrix'!I7 -> 0.025 | F7: ='Cost Matrix'!H7 -> 0.00312 | G7: =E7-F7 -> 0.02188 | H7: =G7*1000 -> 21.88
A8: =Ops!A8 -> table | B8: =Ops!E8 -> anthropic | C8: =INDEX({"anthropic","openai","gemini"},MATCH(MIN('Cost Matrix'!E8:G8),'Cost Matrix'!E8:G8,0)) -> openai | D8: =IF(B8=C8,"✓","→ re-route") -> → re-route | E8: ='Cost Matrix'!I8 -> 0.0135 | F8: ='Cost Matrix'!H8 -> 0.0018 | G8: =E8-F8 -> 0.0117 | H8: =G8*1000 -> 11.7
A9: =Ops!A9 -> redact | B9: =Ops!E9 -> anthropic | C9: =INDEX({"anthropic","openai","gemini"},MATCH(MIN('Cost Matrix'!E9:G9),'Cost Matrix'!E9:G9,0)) -> openai | D9: =IF(B9=C9,"✓","→ re-route") -> → re-route | E9: ='Cost Matrix'!I9 -> 0.01 | F9: ='Cost Matrix'!H9 -> 0.00135 | G9: =E9-F9 -> 0.00865 | H9: =G9*1000 -> 8.65
A10: =Ops!A10 -> generate | B10: =Ops!E10 -> anthropic | C10: =INDEX({"anthropic","openai","gemini"},MATCH(MIN('Cost Matrix'!E10:G10),'Cost Matrix'!E10:G10,0)) -> openai | D10: =IF(B10=C10,"✓","→ re-route") -> → re-route | E10: ='Cost Matrix'!I10 -> 0.042 | F10: ='Cost Matrix'!H10 -> 0.0051 | G10: =E10-F10 -> 0.0369 | H10: =G10*1000 -> 36.9
A11: =Ops!A11 -> sign | B11: =Ops!E11 -> anthropic | C11: =INDEX({"anthropic","openai","gemini"},MATCH(MIN('Cost Matrix'!E11:G11),'Cost Matrix'!E11:G11,0)) -> openai | D11: =IF(B11=C11,"✓","→ re-route") -> → re-route | E11: ='Cost Matrix'!I11 -> 0.0085 | F11: ='Cost Matrix'!H11 -> 0.00105 | G11: =E11-F11 -> 0.00745 | H11: =G11*1000 -> 7.45

Sheet Credit Margin
A1: ASSUMPTIONS
A2: USD / credit (reference) | B2: 0.03 | C2: REFERENCE_USD_MICROS_PER_CREDIT / 1_000_000 from lib/ai/margin-rollup.ts:72 (Pro-pack rate)
A3: Target gross margin | B3: 0.75 | C3: 75% AI-cost-only target; net margin after processor/infra is ~10-15pp lower
A5: Op | B5: Credits | C5: Revenue/call | D5: Current $/call | E5: Cheapest $/call | F5: GM% @ current | G5: GM% @ cheapest | H5: Credit price needed for target @ current | I5: Action
A6: =Ops!A2 -> chat_turn | B6: =Ops!B2 -> 1 | C6: =B6*$B$2 -> 0.03 | D6: ='Cost Matrix'!I2 -> 0.000465 | E6: ='Cost Matrix'!H2 -> 0.000465 | F6: =IF(C6=0,0,(C6-D6)/C6) -> 0.9845 | G6: =IF(C6=0,0,(C6-E6)/C6) -> 0.9845 | H6: =IF(D6=0,0,D6/(1-$B$3)/B6) -> 0.00186 | I6: =IF(F6>=$B$3,"OK",IF(G6>=$B$3,"Re-route to cheapest","Re-price or cap op — current cannot hit target")) -> OK
A7: =Ops!A3 -> summarize | B7: =Ops!B3 -> 3 | C7: =B7*$B$2 -> 0.09 | D7: ='Cost Matrix'!I3 -> 0.011 | E7: ='Cost Matrix'!H3 -> 0.00156 | F7: =IF(C7=0,0,(C7-D7)/C7) -> 0.87777778 | G7: =IF(C7=0,0,(C7-E7)/C7) -> 0.98266667 | H7: =IF(D7=0,0,D7/(1-$B$3)/B7) -> 0.014666667 | I7: =IF(F7>=$B$3,"OK",IF(G7>=$B$3,"Re-route to cheapest","Re-price or cap op — current cannot hit target")) -> OK
A8: =Ops!A4 -> translate | B8: =Ops!B4 -> 5 | C8: =B8*$B$2 -> 0.15 | D8: ='Cost Matrix'!I4 -> 0.0089 | E8: ='Cost Matrix'!H4 -> 0.00237 | F8: =IF(C8=0,0,(C8-D8)/C8) -> 0.94066667 | G8: =IF(C8=0,0,(C8-E8)/C8) -> 0.9842 | H8: =IF(D8=0,0,D8/(1-$B$3)/B8) -> 0.00712 | I8: =IF(F8>=$B$3,"OK",IF(G8>=$B$3,"Re-route to cheapest","Re-price or cap op — current cannot hit target")) -> OK
A9: =Ops!A5 -> ocr | B9: =Ops!B5 -> 2 | C9: =B9*$B$2 -> 0.06 | D9: ='Cost Matrix'!I5 -> 0.00215 | E9: ='Cost Matrix'!H5 -> 0.000555 | F9: =IF(C9=0,0,(C9-D9)/C9) -> 0.96416667 | G9: =IF(C9=0,0,(C9-E9)/C9) -> 0.99075 | H9: =IF(D9=0,0,D9/(1-$B$3)/B9) -> 0.0043 | I9: =IF(F9>=$B$3,"OK",IF(G9>=$B$3,"Re-route to cheapest","Re-price or cap op — current cannot hit target")) -> OK
A10: =Ops!A6 -> compare | B10: =Ops!B6 -> 15 | C10: =B10*$B$2 -> 0.45 | D10: ='Cost Matrix'!I6 -> 0.025 | E10: ='Cost Matrix'!H6 -> 0.00345 | F10: =IF(C10=0,0,(C10-D10)/C10) -> 0.94444444 | G10: =IF(C10=0,0,(C10-E10)/C10) -> 0.99233333 | H10: =IF(D10=0,0,D10/(1-$B$3)/B10) -> 0.0066666667 | I10: =IF(F10>=$B$3,"OK",IF(G10>=$B$3,"Re-route to cheapest","Re-price or cap op — current cannot hit target")) -> OK
A11: =Ops!A7 -> rewrite | B11: =Ops!B7 -> 3 | C11: =B11*$B$2 -> 0.09 | D11: ='Cost Matrix'!I7 -> 0.025 | E11: ='Cost Matrix'!H7 -> 0.00312 | F11: =IF(C11=0,0,(C11-D11)/C11) -> 0.72222222 | G11: =IF(C11=0,0,(C11-E11)/C11) -> 0.96533333 | H11: =IF(D11=0,0,D11/(1-$B$3)/B11) -> 0.033333333 | I11: =IF(F11>=$B$3,"OK",IF(G11>=$B$3,"Re-route to cheapest","Re-price or cap op — current cannot hit target")) -> Re-route to cheapest
A12: =Ops!A8 -> table | B12: =Ops!B8 -> 3 | C12: =B12*$B$2 -> 0.09 | D12: ='Cost Matrix'!I8 -> 0.0135 | E12: ='Cost Matrix'!H8 -> 0.0018 | F12: =IF(C12=0,0,(C12-D12)/C12) -> 0.85 | G12: =IF(C12=0,0,(C12-E12)/C12) -> 0.98 | H12: =IF(D12=0,0,D12/(1-$B$3)/B12) -> 0.018 | I12: =IF(F12>=$B$3,"OK",IF(G12>=$B$3,"Re-route to cheapest","Re-price or cap op — current cannot hit target")) -> OK
A13: =Ops!A9 -> redact | B13: =Ops!B9 -> 5 | C13: =B13*$B$2 -> 0.15 | D13: ='Cost Matrix'!I9 -> 0.01 | E13: ='Cost Matrix'!H9 -> 0.00135 | F13: =IF(C13=0,0,(C13-D13)/C13) -> 0.93333333 | G13: =IF(C13=0,0,(C13-E13)/C13) -> 0.991 | H13: =IF(D13=0,0,D13/(1-$B$3)/B13) -> 0.008 | I13: =IF(F13>=$B$3,"OK",IF(G13>=$B$3,"Re-route to cheapest","Re-price or cap op — current cannot hit target")) -> OK
A14: =Ops!A10 -> generate | B14: =Ops!B10 -> 20 | C14: =B14*$B$2 -> 0.6 | D14: ='Cost Matrix'!I10 -> 0.042 | E14: ='Cost Matrix'!H10 -> 0.0051 | F14: =IF(C14=0,0,(C14-D14)/C14) -> 0.93 | G14: =IF(C14=0,0,(C14-E14)/C14) -> 0.9915 | H14: =IF(D14=0,0,D14/(1-$B$3)/B14) -> 0.0084 | I14: =IF(F14>=$B$3,"OK",IF(G14>=$B$3,"Re-route to cheapest","Re-price or cap op — current cannot hit target")) -> OK
A15: =Ops!A11 -> sign | B15: =Ops!B11 -> 10 | C15: =B15*$B$2 -> 0.3 | D15: ='Cost Matrix'!I11 -> 0.0085 | E15: ='Cost Matrix'!H11 -> 0.00105 | F15: =IF(C15=0,0,(C15-D15)/C15) -> 0.97166667 | G15: =IF(C15=0,0,(C15-E15)/C15) -> 0.9965 | H15: =IF(D15=0,0,D15/(1-$B$3)/B15) -> 0.0034 | I15: =IF(F15>=$B$3,"OK",IF(G15>=$B$3,"Re-route to cheapest","Re-price or cap op — current cannot hit target")) -> OK

Sheet Organic Anchor
A1: REAL DATA — 1st ai_usage row from Hostinger production (gate #3 close)
A3: id | B3: 4aba9e70-918a-4fe5-bc3e-1848609f8f55
A4: user_id | B4: 4e20c284-cecd-4e23-abce-1858cb039ce6
A5: operation | B5: summarize
A6: provider_id | B6: anthropic
A7: model | B7: claude-haiku-4-5-20251001
A8: input_tokens | B8: 1291
A9: output_tokens | B9: 839
A10: latency_ms | B10: 7429
A11: credits_spent | B11: 3
A12: created_at | B12: 2026-04-21 17:25:26.149 UTC
A14: COMPUTED COST (formula):
A15: Cost USD (Anthropic Haiku): | B15: =(B8*Providers!C2+B9*Providers!D2)/1000000 -> 0.005486
A16: Cost if routed to OpenAI 4o-mini: | B16: =(B8*Providers!C4+B9*Providers!D4)/1000000 -> 0.00069705
A17: Cost if routed to Gemini 2.5 Flash: | B17: =(B8*Providers!C5+B9*Providers!D5)/1000000 -> 0.0024848
A19: Revenue @ $0.030/credit: | B19: =B11*0.03 -> 0.09
A20: GM% at Anthropic (actual): | B20: =(B19-B15)/B19 -> 0.93904444
A21: GM% if we had routed to Gemini: | B21: =(B19-B17)/B19 -> 0.97239111
A23: Estimate in margin_scenarios.py (summarize): | B23: 8000 in / 600 out
A24: Real row: | B24: 1291 in / 839 out
A25: Observation: | B25: Real tokens 6.2x lower on input, 1.4x higher on output — summarize estimate is OVER-conservative for short docs
A26: Follow-up: | B26: Re-calibrate OP_TOKENS after 50+ rows accumulate; until then, margin model UNDER-reports true margin
